[
  {
    "id": "c456fdee",
    "title": "브라잘레 버터 500g x 2개 (총 1kg) (업체별도 무료배송)",
    "price": "가격 정보 없음",
    "link": "https://thirtymall.com/detail?id=133025690",
    "found_at": "2026-03-23T22:36:08.691214"
  },
  {
    "id": "42d96013",
    "title": "[한정특가] 베피노 오첼리 무염버터 125g x 3개 (업체별도 무료배송)",
    "price": "가격 정보 없음",
    "link": "https://thirtymall.com/detail?id=132917807",
    "found_at": "2026-03-23T22:36:08.771824"
  },
  {
    "id": "fbb3a0be",
    "title": "[재입고특가] 라꽁비에뜨 프랑스 명품버터 15g x 20개 무염/가염 (업체별도 무료배송)",
    "price": "가격 정보 없음",
    "link": "https://thirtymall.com/detail?id=132585630",
    "found_at": "2026-03-23T22:36:08.871230"
  },
  {
    "id": "67120ac0",
    "title": "[한정특가] 그랑퍼마쥬 씨솔트 꽃소금 버터 250g x 2개입 (업체별도 무료배송)",
    "price": "가격 정보 없음",
    "link": "https://thirtymall.com/detail?id=131985318",
    "found_at": "2026-03-23T22:36:08.965774"
  },
  {
    "id": "9ec56e2d",
    "title": "[한정특가] 라꽁비에뜨 프랑스 무염 가염 명품버터 15g x 30개 (업체별도 무료배송)",
    "price": "가격 정보 없음",
    "link": "https://thirtymall.com/detail?id=131050980",
    "found_at": "2026-03-23T22:36:09.039781"
  },
  {
    "id": "3dc0d6e9",
    "title": "[한정특가] 프리미엄 에쉬레 가염버터 20g*20개입! 최신 한국입항재고! (업체별도 무료배송)",
    "price": "가격 정보 없음",
    "link": "https://thirtymall.com/detail?id=131050920",
    "found_at": "2026-03-23T22:36:09.114509"
  },
  {
    "id": "3146f57c",
    "title": "라꽁비에뜨 프랑스 명품버터 15g x 20개 무염/가염 (업체별도 무료배송)",
    "price": "가격 정보 없음",
    "link": "https://thirtymall.com/detail?id=131050675",
    "found_at": "2026-03-23T22:36:09.188663"
  }
]